fourier_transforms/__init__.py
fourier_transforms/dft.py
fourier_transforms/fft.py
fourier_transforms-0.0.1.dist-info/METADATA
fourier_transforms-0.0.1.dist-info/WHEEL
fourier_transforms-0.0.1.dist-info/top_level.txt
fourier_transforms-0.0.1.dist-info/RECORD
