Metadata-Version: 2.1
Name: fourier-transforms
Version: 0.0.1
Summary: Fast Fourier Transform (FFT) and Discrete Fourier Transform (DFT) implementations
Home-page: https://github.com/ygorbalves/fft-dft-package.git
Author: Ygor
Author-email: ygorbalves222@gmail.com
Requires-Python: >=3.7
Requires-Dist: numpy (==1.23.5)
